pyergon/__init__.py
pyergon/decorators.py
pyergon/core/__init__.py
pyergon/core/call_type.py
pyergon/core/child_flow_error.py
pyergon/core/context.py
pyergon/core/flow_type.py
pyergon/core/invokable_flow.py
pyergon/executor/__init__.py
pyergon/executor/child_completion.py
pyergon/executor/dag.py
pyergon/executor/dag_runtime.py
pyergon/executor/execution.py
pyergon/executor/instance.py
pyergon/executor/outcome.py
pyergon/executor/pending_child.py
pyergon/executor/scheduler.py
pyergon/executor/signal.py
pyergon/executor/suspension_payload.py
pyergon/executor/timer.py
pyergon/executor/worker.py
pyergon/models/__init__.py
pyergon/models/invocation.py
pyergon/models/retry.py
pyergon/models/scheduled_flow.py
pyergon/models/status.py
pyergon/models/timer_info.py
pyergon/storage/__init__.py
pyergon/storage/base.py
pyergon/storage/memory.py
pyergon/storage/redis.py
pyergon/storage/sqlite.py
pyergon-0.8.1.dist-info/METADATA
pyergon-0.8.1.dist-info/WHEEL
pyergon-0.8.1.dist-info/top_level.txt
pyergon-0.8.1.dist-info/RECORD
