Metadata-Version: 2.4
Name: pyergon
Version: 0.8.1
Summary: Durable execution framework for Python
Author: Richard chukwu
Keywords: workflow,durable-execution,temporal,async,llm
Classifier: Development Status :: 3 - Alpha
Classifier: Intended Audience :: Developers
Classifier: License :: OSI Approved :: MIT License
Classifier: License :: OSI Approved :: Apache Software License
Classifier: Programming Language :: Python :: 3.11
Classifier: Programming Language :: Python :: 3.12
Classifier: Topic :: Software Development :: Libraries
Requires-Python: >=3.11
Requires-Dist: aiosqlite==0.21.0
Requires-Dist: redis[hiredis]<6.5,>=5.0.0
Requires-Dist: numpy==2.4.1
Requires-Dist: uuid7>=0.1.0
Requires-Dist: xxhash>=3.0.0
Requires-Dist: celery[redis]>=5.4.0
Provides-Extra: dev
Requires-Dist: pytest==9.0.1; extra == "dev"
Requires-Dist: pytest-asyncio==1.3.0; extra == "dev"
Requires-Dist: pytest-timeout==2.4.0; extra == "dev"
Requires-Dist: pytest-xdist>=3.0; extra == "dev"
Requires-Dist: pytest-cov==7.0.0; extra == "dev"
Requires-Dist: hypothesis==6.148.8; extra == "dev"
Requires-Dist: mutmut==3.4.0; extra == "dev"
Requires-Dist: black>=23.0; extra == "dev"
Requires-Dist: mypy==1.19.0; extra == "dev"
Requires-Dist: ruff==0.14.6; extra == "dev"
